{
"tbm_fpx_payment_ac_b2b": [
	{
		"rsp_exchangeid" : "EX00020258",
		"rsp_sellerid" : "SE00026898",
		"rsp_order_no" : "ZP2B231215000041",
		"rsp_session_order" : null,
		"rsp_datetime" : "2023-12-15 23:40:08",
		"rsp_amt" : 30000.0,
		"rsp_status" : "PENDING",
		"rsp_st_code" : "99",
		"rsp_rsp_code" : null,
		"rsp_bankcode" : "TEST0021",
		"rsp_fpx_id" : "2312152340080880",
		"rsp_bank_branch" : "SBI BANK A",
		"rsp_paymode" : "FPX",
		"rsp_dt_authid" : null,
		"rsp_ct_authid" : "99",
		"rsp_from" : 1
	},
	{
		"rsp_exchangeid" : "EX00020258",
		"rsp_sellerid" : "SE00026898",
		"rsp_order_no" : "ZP2B231216000042",
		"rsp_session_order" : null,
		"rsp_datetime" : "2023-12-16 13:02:24",
		"rsp_amt" : 30000.0,
		"rsp_status" : "PENDING",
		"rsp_st_code" : "99",
		"rsp_rsp_code" : null,
		"rsp_bankcode" : "TEST0021",
		"rsp_fpx_id" : "2312161302240958",
		"rsp_bank_branch" : "SBI BANK A",
		"rsp_paymode" : "FPX",
		"rsp_dt_authid" : null,
		"rsp_ct_authid" : "99",
		"rsp_from" : 1
	},
	{
		"rsp_exchangeid" : "EX00020258",
		"rsp_sellerid" : "SE00026898",
		"rsp_order_no" : "ZP2B231216000042",
		"rsp_session_order" : null,
		"rsp_datetime" : "2023-12-16 13:02:24",
		"rsp_amt" : 30000.0,
		"rsp_status" : "UNSUCCESSFUL",
		"rsp_st_code" : "OF",
		"rsp_rsp_code" : null,
		"rsp_bankcode" : "TEST0021",
		"rsp_fpx_id" : "2312161302240958",
		"rsp_bank_branch" : "SBI BANK A",
		"rsp_paymode" : "FPX",
		"rsp_dt_authid" : null,
		"rsp_ct_authid" : "OF",
		"rsp_from" : 1
	},
	{
		"rsp_exchangeid" : "EX00020258",
		"rsp_sellerid" : "SE00026898",
		"rsp_order_no" : "ZP2B231218000044",
		"rsp_session_order" : null,
		"rsp_datetime" : "2023-12-18 12:05:35",
		"rsp_amt" : 10000.0,
		"rsp_status" : "PENDING",
		"rsp_st_code" : "99",
		"rsp_rsp_code" : null,
		"rsp_bankcode" : "TEST0022",
		"rsp_fpx_id" : "2312181205350757",
		"rsp_bank_branch" : "SBI BANK B",
		"rsp_paymode" : "FPX",
		"rsp_dt_authid" : null,
		"rsp_ct_authid" : "99",
		"rsp_from" : 1
	},
	{
		"rsp_exchangeid" : "EX00020258",
		"rsp_sellerid" : "SE00026898",
		"rsp_order_no" : "ZP2B231218000044",
		"rsp_session_order" : null,
		"rsp_datetime" : "2023-12-18 12:05:35",
		"rsp_amt" : 10000.0,
		"rsp_status" : "UNSUCCESSFUL",
		"rsp_st_code" : "OF",
		"rsp_rsp_code" : null,
		"rsp_bankcode" : "TEST0022",
		"rsp_fpx_id" : "2312181205350757",
		"rsp_bank_branch" : "SBI BANK B",
		"rsp_paymode" : "FPX",
		"rsp_dt_authid" : null,
		"rsp_ct_authid" : "OF",
		"rsp_from" : 1
	},
	{
		"rsp_exchangeid" : "EX00020258",
		"rsp_sellerid" : "SE00026898",
		"rsp_order_no" : "ZP2B231218000045",
		"rsp_session_order" : null,
		"rsp_datetime" : "2023-12-18 12:06:14",
		"rsp_amt" : 10000.0,
		"rsp_status" : "UNSUCCESSFUL",
		"rsp_st_code" : "51",
		"rsp_rsp_code" : null,
		"rsp_bankcode" : "TEST0022",
		"rsp_fpx_id" : "2312181206140758",
		"rsp_bank_branch" : "SBI BANK B",
		"rsp_paymode" : "FPX",
		"rsp_dt_authid" : null,
		"rsp_ct_authid" : "51",
		"rsp_from" : 1
	},
	{
		"rsp_exchangeid" : "EX00020258",
		"rsp_sellerid" : "SE00026898",
		"rsp_order_no" : "ZP2B231218000045",
		"rsp_session_order" : null,
		"rsp_datetime" : "2023-12-18 12:06:14",
		"rsp_amt" : 10000.0,
		"rsp_status" : "PENDING",
		"rsp_st_code" : "99",
		"rsp_rsp_code" : null,
		"rsp_bankcode" : "TEST0022",
		"rsp_fpx_id" : "2312181206140758",
		"rsp_bank_branch" : "SBI BANK B",
		"rsp_paymode" : "FPX",
		"rsp_dt_authid" : null,
		"rsp_ct_authid" : "99",
		"rsp_from" : 1
	},
	{
		"rsp_exchangeid" : "EX00020258",
		"rsp_sellerid" : "SE00026898",
		"rsp_order_no" : "ZP2B231218000046",
		"rsp_session_order" : null,
		"rsp_datetime" : "2023-12-18 12:15:25",
		"rsp_amt" : 30000.0,
		"rsp_status" : "SUCCESSFUL",
		"rsp_st_code" : "00",
		"rsp_rsp_code" : null,
		"rsp_bankcode" : "TEST0021",
		"rsp_fpx_id" : "2312181215250771",
		"rsp_bank_branch" : "SBI BANK A",
		"rsp_paymode" : "FPX",
		"rsp_dt_authid" : null,
		"rsp_ct_authid" : "00",
		"rsp_from" : 1
	},
	{
		"rsp_exchangeid" : "EX00020258",
		"rsp_sellerid" : "SE00026898",
		"rsp_order_no" : "ZP2B231218000046",
		"rsp_session_order" : null,
		"rsp_datetime" : "2023-12-18 12:15:25",
		"rsp_amt" : 30000.0,
		"rsp_status" : "PENDING",
		"rsp_st_code" : "99",
		"rsp_rsp_code" : null,
		"rsp_bankcode" : "TEST0021",
		"rsp_fpx_id" : "2312181215250771",
		"rsp_bank_branch" : "SBI BANK A",
		"rsp_paymode" : "FPX",
		"rsp_dt_authid" : null,
		"rsp_ct_authid" : "99",
		"rsp_from" : 1
	},
	{
		"rsp_exchangeid" : "EX00020258",
		"rsp_sellerid" : "SE00026898",
		"rsp_order_no" : "ZP2B231218000047",
		"rsp_session_order" : null,
		"rsp_datetime" : "2023-12-18 12:43:04",
		"rsp_amt" : 30000.5,
		"rsp_status" : "PENDING",
		"rsp_st_code" : "99",
		"rsp_rsp_code" : null,
		"rsp_bankcode" : "TEST0021",
		"rsp_fpx_id" : "2312181243040814",
		"rsp_bank_branch" : "SBI BANK A",
		"rsp_paymode" : "FPX",
		"rsp_dt_authid" : null,
		"rsp_ct_authid" : "99",
		"rsp_from" : 1
	},
	{
		"rsp_exchangeid" : "EX00020258",
		"rsp_sellerid" : "SE00026898",
		"rsp_order_no" : "ZP2B231218000047",
		"rsp_session_order" : null,
		"rsp_datetime" : "2023-12-18 12:43:04",
		"rsp_amt" : 30000.5,
		"rsp_status" : "UNSUCCESSFUL",
		"rsp_st_code" : "OF",
		"rsp_rsp_code" : null,
		"rsp_bankcode" : "TEST0021",
		"rsp_fpx_id" : "2312181243040814",
		"rsp_bank_branch" : "SBI BANK A",
		"rsp_paymode" : "FPX",
		"rsp_dt_authid" : null,
		"rsp_ct_authid" : "OF",
		"rsp_from" : 1
	},
	{
		"rsp_exchangeid" : "EX00020258",
		"rsp_sellerid" : "SE00026898",
		"rsp_order_no" : "ZP2B231218000048",
		"rsp_session_order" : null,
		"rsp_datetime" : "2023-12-18 12:49:50",
		"rsp_amt" : 30000.0,
		"rsp_status" : "SUCCESSFUL",
		"rsp_st_code" : "00",
		"rsp_rsp_code" : null,
		"rsp_bankcode" : "TEST0021",
		"rsp_fpx_id" : "2312181249500821",
		"rsp_bank_branch" : "SBI BANK A",
		"rsp_paymode" : "FPX",
		"rsp_dt_authid" : null,
		"rsp_ct_authid" : "00",
		"rsp_from" : 1
	},
	{
		"rsp_exchangeid" : "EX00020258",
		"rsp_sellerid" : "SE00026898",
		"rsp_order_no" : "ZP2B231218000048",
		"rsp_session_order" : null,
		"rsp_datetime" : "2023-12-18 12:49:50",
		"rsp_amt" : 30000.0,
		"rsp_status" : "PENDING",
		"rsp_st_code" : "99",
		"rsp_rsp_code" : null,
		"rsp_bankcode" : "TEST0021",
		"rsp_fpx_id" : "2312181249500821",
		"rsp_bank_branch" : "SBI BANK A",
		"rsp_paymode" : "FPX",
		"rsp_dt_authid" : null,
		"rsp_ct_authid" : "99",
		"rsp_from" : 1
	},
	{
		"rsp_exchangeid" : "EX00020258",
		"rsp_sellerid" : "SE00026898",
		"rsp_order_no" : "ZP2B231218000049",
		"rsp_session_order" : null,
		"rsp_datetime" : "2023-12-18 14:04:29",
		"rsp_amt" : 30000.0,
		"rsp_status" : "SUCCESSFUL",
		"rsp_st_code" : "00",
		"rsp_rsp_code" : null,
		"rsp_bankcode" : "TEST0022",
		"rsp_fpx_id" : "2312181404290911",
		"rsp_bank_branch" : "SBI BANK B",
		"rsp_paymode" : "FPX",
		"rsp_dt_authid" : null,
		"rsp_ct_authid" : "00",
		"rsp_from" : 1
	},
	{
		"rsp_exchangeid" : "EX00020258",
		"rsp_sellerid" : "SE00026898",
		"rsp_order_no" : "ZP2B231218000049",
		"rsp_session_order" : null,
		"rsp_datetime" : "2023-12-18 14:04:29",
		"rsp_amt" : 30000.0,
		"rsp_status" : "PENDING",
		"rsp_st_code" : "99",
		"rsp_rsp_code" : null,
		"rsp_bankcode" : "TEST0022",
		"rsp_fpx_id" : "2312181404290911",
		"rsp_bank_branch" : "SBI BANK B",
		"rsp_paymode" : "FPX",
		"rsp_dt_authid" : null,
		"rsp_ct_authid" : "99",
		"rsp_from" : 1
	},
	{
		"rsp_exchangeid" : "EX00020258",
		"rsp_sellerid" : "SE00026898",
		"rsp_order_no" : "ZP2B231218000053",
		"rsp_session_order" : null,
		"rsp_datetime" : "2023-12-18 14:51:43",
		"rsp_amt" : 30000.0,
		"rsp_status" : "SUCCESSFUL",
		"rsp_st_code" : "00",
		"rsp_rsp_code" : null,
		"rsp_bankcode" : "TEST0021",
		"rsp_fpx_id" : "2312181451430061",
		"rsp_bank_branch" : "SBI BANK A",
		"rsp_paymode" : "FPX",
		"rsp_dt_authid" : null,
		"rsp_ct_authid" : "00",
		"rsp_from" : 1
	},
	{
		"rsp_exchangeid" : "EX00020258",
		"rsp_sellerid" : "SE00026898",
		"rsp_order_no" : "ZP2B231218000053",
		"rsp_session_order" : null,
		"rsp_datetime" : "2023-12-18 14:51:43",
		"rsp_amt" : 30000.0,
		"rsp_status" : "PENDING",
		"rsp_st_code" : "99",
		"rsp_rsp_code" : null,
		"rsp_bankcode" : "TEST0021",
		"rsp_fpx_id" : "2312181451430061",
		"rsp_bank_branch" : "SBI BANK A",
		"rsp_paymode" : "FPX",
		"rsp_dt_authid" : null,
		"rsp_ct_authid" : "99",
		"rsp_from" : 1
	},
	{
		"rsp_exchangeid" : "EX00020258",
		"rsp_sellerid" : "SE00026898",
		"rsp_order_no" : "ZP2B231218000054",
		"rsp_session_order" : null,
		"rsp_datetime" : "2023-12-18 14:58:12",
		"rsp_amt" : 30000.0,
		"rsp_status" : "UNSUCCESSFUL",
		"rsp_st_code" : "51",
		"rsp_rsp_code" : null,
		"rsp_bankcode" : "TEST0022",
		"rsp_fpx_id" : "2312181458120085",
		"rsp_bank_branch" : "SBI BANK B",
		"rsp_paymode" : "FPX",
		"rsp_dt_authid" : null,
		"rsp_ct_authid" : "51",
		"rsp_from" : 1
	},
	{
		"rsp_exchangeid" : "EX00020258",
		"rsp_sellerid" : "SE00026898",
		"rsp_order_no" : "ZP2B231218000054",
		"rsp_session_order" : null,
		"rsp_datetime" : "2023-12-18 14:58:12",
		"rsp_amt" : 30000.0,
		"rsp_status" : "PENDING",
		"rsp_st_code" : "99",
		"rsp_rsp_code" : null,
		"rsp_bankcode" : "TEST0022",
		"rsp_fpx_id" : "2312181458120085",
		"rsp_bank_branch" : "SBI BANK B",
		"rsp_paymode" : "FPX",
		"rsp_dt_authid" : null,
		"rsp_ct_authid" : "99",
		"rsp_from" : 1
	},
	{
		"rsp_exchangeid" : "EX00020258",
		"rsp_sellerid" : "SE00026898",
		"rsp_order_no" : "ZP2B231219000063",
		"rsp_session_order" : null,
		"rsp_datetime" : "2023-12-19 22:29:59",
		"rsp_amt" : 30000.0,
		"rsp_status" : "SUCCESSFUL",
		"rsp_st_code" : "00",
		"rsp_rsp_code" : null,
		"rsp_bankcode" : "TEST0021",
		"rsp_fpx_id" : "2312192229590617",
		"rsp_bank_branch" : "SBI BANK A",
		"rsp_paymode" : "FPX",
		"rsp_dt_authid" : null,
		"rsp_ct_authid" : "00",
		"rsp_from" : 1
	},
	{
		"rsp_exchangeid" : "EX00020258",
		"rsp_sellerid" : "SE00026898",
		"rsp_order_no" : "ZP2B231219000063",
		"rsp_session_order" : null,
		"rsp_datetime" : "2023-12-19 22:29:59",
		"rsp_amt" : 30000.0,
		"rsp_status" : "PENDING",
		"rsp_st_code" : "99",
		"rsp_rsp_code" : null,
		"rsp_bankcode" : "TEST0021",
		"rsp_fpx_id" : "2312192229590617",
		"rsp_bank_branch" : "SBI BANK A",
		"rsp_paymode" : "FPX",
		"rsp_dt_authid" : null,
		"rsp_ct_authid" : "99",
		"rsp_from" : 1
	},
	{
		"rsp_exchangeid" : "EX00020258",
		"rsp_sellerid" : "SE00026898",
		"rsp_order_no" : "ZP2B231219000064",
		"rsp_session_order" : null,
		"rsp_datetime" : "2023-12-19 22:42:46",
		"rsp_amt" : 19000.0,
		"rsp_status" : "UNSUCCESSFUL",
		"rsp_st_code" : "51",
		"rsp_rsp_code" : null,
		"rsp_bankcode" : "TEST0022",
		"rsp_fpx_id" : "2312192242460649",
		"rsp_bank_branch" : "SBI BANK B",
		"rsp_paymode" : "FPX",
		"rsp_dt_authid" : null,
		"rsp_ct_authid" : "51",
		"rsp_from" : 1
	},
	{
		"rsp_exchangeid" : "EX00020258",
		"rsp_sellerid" : "SE00026898",
		"rsp_order_no" : "ZP2B231219000064",
		"rsp_session_order" : null,
		"rsp_datetime" : "2023-12-19 22:42:46",
		"rsp_amt" : 19000.0,
		"rsp_status" : "PENDING",
		"rsp_st_code" : "99",
		"rsp_rsp_code" : null,
		"rsp_bankcode" : "TEST0022",
		"rsp_fpx_id" : "2312192242460649",
		"rsp_bank_branch" : "SBI BANK B",
		"rsp_paymode" : "FPX",
		"rsp_dt_authid" : null,
		"rsp_ct_authid" : "99",
		"rsp_from" : 1
	},
	{
		"rsp_exchangeid" : "EX00020258",
		"rsp_sellerid" : "SE00026898",
		"rsp_order_no" : "ZP2B231219000066",
		"rsp_session_order" : null,
		"rsp_datetime" : "0000-00-00 00:00:00",
		"rsp_amt" : 999999.99,
		"rsp_status" : "UNSUCCESSFUL",
		"rsp_st_code" : "48",
		"rsp_rsp_code" : null,
		"rsp_bankcode" : "TEST0021",
		"rsp_fpx_id" : "",
		"rsp_bank_branch" : "",
		"rsp_paymode" : "FPX",
		"rsp_dt_authid" : null,
		"rsp_ct_authid" : "48",
		"rsp_from" : 1
	},
	{
		"rsp_exchangeid" : "EX00020258",
		"rsp_sellerid" : "SE00026898",
		"rsp_order_no" : "ZP2B231220000069",
		"rsp_session_order" : null,
		"rsp_datetime" : "0000-00-00 00:00:00",
		"rsp_amt" : 1.99,
		"rsp_status" : "UNSUCCESSFUL",
		"rsp_st_code" : "2A",
		"rsp_rsp_code" : null,
		"rsp_bankcode" : "TEST0021",
		"rsp_fpx_id" : "",
		"rsp_bank_branch" : "",
		"rsp_paymode" : "FPX",
		"rsp_dt_authid" : null,
		"rsp_ct_authid" : "2A",
		"rsp_from" : 1
	},
	{
		"rsp_exchangeid" : "EX00020258",
		"rsp_sellerid" : "SE00026898",
		"rsp_order_no" : "ZP2B231220000071",
		"rsp_session_order" : null,
		"rsp_datetime" : "2023-12-20 22:27:30",
		"rsp_amt" : 30000.0,
		"rsp_status" : "PENDING",
		"rsp_st_code" : "99",
		"rsp_rsp_code" : null,
		"rsp_bankcode" : "TEST0021",
		"rsp_fpx_id" : "2312202227300495",
		"rsp_bank_branch" : "SBI BANK A",
		"rsp_paymode" : "FPX",
		"rsp_dt_authid" : null,
		"rsp_ct_authid" : "99",
		"rsp_from" : 1
	},
	{
		"rsp_exchangeid" : "EX00020258",
		"rsp_sellerid" : "SE00026898",
		"rsp_order_no" : "ZP2B231220000071",
		"rsp_session_order" : null,
		"rsp_datetime" : "2023-12-20 22:27:30",
		"rsp_amt" : 30000.0,
		"rsp_status" : "UNSUCCESSFUL",
		"rsp_st_code" : "OF",
		"rsp_rsp_code" : null,
		"rsp_bankcode" : "TEST0021",
		"rsp_fpx_id" : "2312202227300495",
		"rsp_bank_branch" : "SBI BANK A",
		"rsp_paymode" : "FPX",
		"rsp_dt_authid" : null,
		"rsp_ct_authid" : "OF",
		"rsp_from" : 1
	},
	{
		"rsp_exchangeid" : "EX00020258",
		"rsp_sellerid" : "SE00026898",
		"rsp_order_no" : "ZP2B231220000073",
		"rsp_session_order" : null,
		"rsp_datetime" : "2023-12-20 23:03:33",
		"rsp_amt" : 30000.0,
		"rsp_status" : "SUCCESSFUL",
		"rsp_st_code" : "00",
		"rsp_rsp_code" : null,
		"rsp_bankcode" : "TEST0021",
		"rsp_fpx_id" : "2312202303330506",
		"rsp_bank_branch" : "SBI BANK A",
		"rsp_paymode" : "FPX",
		"rsp_dt_authid" : null,
		"rsp_ct_authid" : "00",
		"rsp_from" : 1
	},
	{
		"rsp_exchangeid" : "EX00020258",
		"rsp_sellerid" : "SE00026898",
		"rsp_order_no" : "ZP2B231220000073",
		"rsp_session_order" : null,
		"rsp_datetime" : "2023-12-20 23:03:33",
		"rsp_amt" : 30000.0,
		"rsp_status" : "PENDING",
		"rsp_st_code" : "99",
		"rsp_rsp_code" : null,
		"rsp_bankcode" : "TEST0021",
		"rsp_fpx_id" : "2312202303330506",
		"rsp_bank_branch" : "SBI BANK A",
		"rsp_paymode" : "FPX",
		"rsp_dt_authid" : null,
		"rsp_ct_authid" : "99",
		"rsp_from" : 1
	},
	{
		"rsp_exchangeid" : "EX00020258",
		"rsp_sellerid" : "SE00026898",
		"rsp_order_no" : "ZP2B231220000074",
		"rsp_session_order" : null,
		"rsp_datetime" : "2023-12-20 23:33:52",
		"rsp_amt" : 50000.0,
		"rsp_status" : "UNSUCCESSFUL",
		"rsp_st_code" : "51",
		"rsp_rsp_code" : null,
		"rsp_bankcode" : "TEST0022",
		"rsp_fpx_id" : "2312202333510515",
		"rsp_bank_branch" : "SBI BANK B",
		"rsp_paymode" : "FPX",
		"rsp_dt_authid" : null,
		"rsp_ct_authid" : "51",
		"rsp_from" : 1
	},
	{
		"rsp_exchangeid" : "EX00020258",
		"rsp_sellerid" : "SE00026898",
		"rsp_order_no" : "ZP2B231220000074",
		"rsp_session_order" : null,
		"rsp_datetime" : "2023-12-20 23:33:52",
		"rsp_amt" : 50000.0,
		"rsp_status" : "PENDING",
		"rsp_st_code" : "99",
		"rsp_rsp_code" : null,
		"rsp_bankcode" : "TEST0022",
		"rsp_fpx_id" : "2312202333510515",
		"rsp_bank_branch" : "SBI BANK B",
		"rsp_paymode" : "FPX",
		"rsp_dt_authid" : null,
		"rsp_ct_authid" : "99",
		"rsp_from" : 1
	},
	{
		"rsp_exchangeid" : "EX00020258",
		"rsp_sellerid" : "SE00026898",
		"rsp_order_no" : "ZP2B231221000077",
		"rsp_session_order" : null,
		"rsp_datetime" : "2023-12-21 16:27:42",
		"rsp_amt" : 30000.0,
		"rsp_status" : "SUCCESSFUL",
		"rsp_st_code" : "00",
		"rsp_rsp_code" : null,
		"rsp_bankcode" : "TEST0021",
		"rsp_fpx_id" : "2312211627420635",
		"rsp_bank_branch" : "SBI BANK A",
		"rsp_paymode" : "FPX",
		"rsp_dt_authid" : null,
		"rsp_ct_authid" : "00",
		"rsp_from" : 1
	},
	{
		"rsp_exchangeid" : "EX00020258",
		"rsp_sellerid" : "SE00026898",
		"rsp_order_no" : "ZP2B231221000077",
		"rsp_session_order" : null,
		"rsp_datetime" : "2023-12-21 16:27:42",
		"rsp_amt" : 30000.0,
		"rsp_status" : "PENDING",
		"rsp_st_code" : "99",
		"rsp_rsp_code" : null,
		"rsp_bankcode" : "TEST0021",
		"rsp_fpx_id" : "2312211627420635",
		"rsp_bank_branch" : "SBI BANK A",
		"rsp_paymode" : "FPX",
		"rsp_dt_authid" : null,
		"rsp_ct_authid" : "99",
		"rsp_from" : 1
	},
	{
		"rsp_exchangeid" : "EX00020258",
		"rsp_sellerid" : "SE00026898",
		"rsp_order_no" : "ZP2B231221000078",
		"rsp_session_order" : null,
		"rsp_datetime" : "2023-12-21 17:32:55",
		"rsp_amt" : 190000.0,
		"rsp_status" : "UNSUCCESSFUL",
		"rsp_st_code" : "51",
		"rsp_rsp_code" : null,
		"rsp_bankcode" : "TEST0022",
		"rsp_fpx_id" : "2312211732550829",
		"rsp_bank_branch" : "SBI BANK B",
		"rsp_paymode" : "FPX",
		"rsp_dt_authid" : null,
		"rsp_ct_authid" : "51",
		"rsp_from" : 1
	},
	{
		"rsp_exchangeid" : "EX00020258",
		"rsp_sellerid" : "SE00026898",
		"rsp_order_no" : "ZP2B231221000078",
		"rsp_session_order" : null,
		"rsp_datetime" : "2023-12-21 17:32:55",
		"rsp_amt" : 190000.0,
		"rsp_status" : "PENDING",
		"rsp_st_code" : "99",
		"rsp_rsp_code" : null,
		"rsp_bankcode" : "TEST0022",
		"rsp_fpx_id" : "2312211732550829",
		"rsp_bank_branch" : "SBI BANK B",
		"rsp_paymode" : "FPX",
		"rsp_dt_authid" : null,
		"rsp_ct_authid" : "99",
		"rsp_from" : 1
	},
	{
		"rsp_exchangeid" : "EX00020258",
		"rsp_sellerid" : "SE00026898",
		"rsp_order_no" : "ZP2B231221000079",
		"rsp_session_order" : null,
		"rsp_datetime" : "0000-00-00 00:00:00",
		"rsp_amt" : 1.9,
		"rsp_status" : "UNSUCCESSFUL",
		"rsp_st_code" : "2A",
		"rsp_rsp_code" : null,
		"rsp_bankcode" : "TEST0021",
		"rsp_fpx_id" : "",
		"rsp_bank_branch" : "",
		"rsp_paymode" : "FPX",
		"rsp_dt_authid" : null,
		"rsp_ct_authid" : "2A",
		"rsp_from" : 1
	},
	{
		"rsp_exchangeid" : "EX00020258",
		"rsp_sellerid" : "SE00026898",
		"rsp_order_no" : "ZP2B231221000080",
		"rsp_session_order" : null,
		"rsp_datetime" : "0000-00-00 00:00:00",
		"rsp_amt" : 1.99,
		"rsp_status" : "UNSUCCESSFUL",
		"rsp_st_code" : "2A",
		"rsp_rsp_code" : null,
		"rsp_bankcode" : "TEST0021",
		"rsp_fpx_id" : "",
		"rsp_bank_branch" : "",
		"rsp_paymode" : "FPX",
		"rsp_dt_authid" : null,
		"rsp_ct_authid" : "2A",
		"rsp_from" : 1
	},
	{
		"rsp_exchangeid" : "EX00020258",
		"rsp_sellerid" : "SE00026898",
		"rsp_order_no" : "ZP2B231221000081",
		"rsp_session_order" : null,
		"rsp_datetime" : "0000-00-00 00:00:00",
		"rsp_amt" : 999999.99,
		"rsp_status" : "UNSUCCESSFUL",
		"rsp_st_code" : "48",
		"rsp_rsp_code" : null,
		"rsp_bankcode" : "TEST0021",
		"rsp_fpx_id" : "",
		"rsp_bank_branch" : "",
		"rsp_paymode" : "FPX",
		"rsp_dt_authid" : null,
		"rsp_ct_authid" : "48",
		"rsp_from" : 1
	},
	{
		"rsp_exchangeid" : "EX00020258",
		"rsp_sellerid" : "SE00026898",
		"rsp_order_no" : "ZP2B231221000082",
		"rsp_session_order" : null,
		"rsp_datetime" : "0000-00-00 00:00:00",
		"rsp_amt" : 999999.99,
		"rsp_status" : "UNSUCCESSFUL",
		"rsp_st_code" : "48",
		"rsp_rsp_code" : null,
		"rsp_bankcode" : "TEST0021",
		"rsp_fpx_id" : "",
		"rsp_bank_branch" : "",
		"rsp_paymode" : "FPX",
		"rsp_dt_authid" : null,
		"rsp_ct_authid" : "48",
		"rsp_from" : 1
	},
	{
		"rsp_exchangeid" : "EX00020258",
		"rsp_sellerid" : "SE00026898",
		"rsp_order_no" : "ZP2B231221000083",
		"rsp_session_order" : null,
		"rsp_datetime" : "0000-00-00 00:00:00",
		"rsp_amt" : 1.99,
		"rsp_status" : "UNSUCCESSFUL",
		"rsp_st_code" : "2A",
		"rsp_rsp_code" : null,
		"rsp_bankcode" : "TEST0021",
		"rsp_fpx_id" : "",
		"rsp_bank_branch" : "",
		"rsp_paymode" : "FPX",
		"rsp_dt_authid" : null,
		"rsp_ct_authid" : "2A",
		"rsp_from" : 1
	},
	{
		"rsp_exchangeid" : "EX00020258",
		"rsp_sellerid" : "SE00026898",
		"rsp_order_no" : "ZP2B231221000085",
		"rsp_session_order" : null,
		"rsp_datetime" : "2023-12-21 23:55:56",
		"rsp_amt" : 30000.0,
		"rsp_status" : "PENDING",
		"rsp_st_code" : "99",
		"rsp_rsp_code" : null,
		"rsp_bankcode" : "TEST0021",
		"rsp_fpx_id" : "2312212355560180",
		"rsp_bank_branch" : "SBI BANK A",
		"rsp_paymode" : "FPX",
		"rsp_dt_authid" : null,
		"rsp_ct_authid" : "99",
		"rsp_from" : 1
	},
	{
		"rsp_exchangeid" : "EX00020258",
		"rsp_sellerid" : "SE00026898",
		"rsp_order_no" : "ZP2B231221000085",
		"rsp_session_order" : null,
		"rsp_datetime" : "2023-12-21 23:55:56",
		"rsp_amt" : 30000.0,
		"rsp_status" : "UNSUCCESSFUL",
		"rsp_st_code" : "OF",
		"rsp_rsp_code" : null,
		"rsp_bankcode" : "TEST0021",
		"rsp_fpx_id" : "2312212355560180",
		"rsp_bank_branch" : "SBI BANK A",
		"rsp_paymode" : "FPX",
		"rsp_dt_authid" : null,
		"rsp_ct_authid" : "OF",
		"rsp_from" : 1
	},
	{
		"rsp_exchangeid" : "EX00020258",
		"rsp_sellerid" : "SE00026898",
		"rsp_order_no" : "ZP2B231222000087",
		"rsp_session_order" : null,
		"rsp_datetime" : "2023-12-22 18:34:01",
		"rsp_amt" : 30000.0,
		"rsp_status" : "SUCCESSFUL",
		"rsp_st_code" : "00",
		"rsp_rsp_code" : null,
		"rsp_bankcode" : "TEST0021",
		"rsp_fpx_id" : "2312221834010629",
		"rsp_bank_branch" : "SBI BANK A",
		"rsp_paymode" : "FPX",
		"rsp_dt_authid" : null,
		"rsp_ct_authid" : "00",
		"rsp_from" : 1
	},
	{
		"rsp_exchangeid" : "EX00020258",
		"rsp_sellerid" : "SE00026898",
		"rsp_order_no" : "ZP2B231222000087",
		"rsp_session_order" : null,
		"rsp_datetime" : "2023-12-22 18:34:01",
		"rsp_amt" : 30000.0,
		"rsp_status" : "PENDING",
		"rsp_st_code" : "99",
		"rsp_rsp_code" : null,
		"rsp_bankcode" : "TEST0021",
		"rsp_fpx_id" : "2312221834010629",
		"rsp_bank_branch" : "SBI BANK A",
		"rsp_paymode" : "FPX",
		"rsp_dt_authid" : null,
		"rsp_ct_authid" : "99",
		"rsp_from" : 1
	},
	{
		"rsp_exchangeid" : "EX00020258",
		"rsp_sellerid" : "SE00026898",
		"rsp_order_no" : "ZP2B231228000089",
		"rsp_session_order" : null,
		"rsp_datetime" : "2023-12-28 11:26:48",
		"rsp_amt" : 30000.0,
		"rsp_status" : "SUCCESSFUL",
		"rsp_st_code" : "00",
		"rsp_rsp_code" : null,
		"rsp_bankcode" : "TEST0021",
		"rsp_fpx_id" : "2312281126480888",
		"rsp_bank_branch" : "SBI BANK A",
		"rsp_paymode" : "FPX",
		"rsp_dt_authid" : null,
		"rsp_ct_authid" : "00",
		"rsp_from" : 1
	},
	{
		"rsp_exchangeid" : "EX00020258",
		"rsp_sellerid" : "SE00026898",
		"rsp_order_no" : "ZP2B231228000089",
		"rsp_session_order" : null,
		"rsp_datetime" : "2023-12-28 11:26:48",
		"rsp_amt" : 30000.0,
		"rsp_status" : "PENDING",
		"rsp_st_code" : "99",
		"rsp_rsp_code" : null,
		"rsp_bankcode" : "TEST0021",
		"rsp_fpx_id" : "2312281126480888",
		"rsp_bank_branch" : "SBI BANK A",
		"rsp_paymode" : "FPX",
		"rsp_dt_authid" : null,
		"rsp_ct_authid" : "99",
		"rsp_from" : 1
	}
]}
